{
  "type": "File",
  "start": 0,
  "end": 276,
  "loc": {
    "start": {
      "line": 1,
      "column": 0,
      "index": 0
    },
    "end": {
      "line": 16,
      "column": 0,
      "index": 276
    }
  },
  "range": [
    0,
    276
  ],
  "errors": [],
  "program": {
    "type": "Program",
    "start": 0,
    "end": 276,
    "loc": {
      "start": {
        "line": 1,
        "column": 0,
        "index": 0
      },
      "end": {
        "line": 16,
        "column": 0,
        "index": 276
      }
    },
    "range": [
      0,
      276
    ],
    "sourceType": "module",
    "interpreter": null,
    "body": [
      {
        "type": "FunctionDeclaration",
        "start": 0,
        "end": 251,
        "loc": {
          "start": {
            "line": 1,
            "column": 0,
            "index": 0
          },
          "end": {
            "line": 14,
            "column": 1,
            "index": 251
          }
        },
        "range": [
          0,
          251
        ],
        "id": {
          "type": "Identifier",
          "start": 9,
          "end": 19,
          "loc": {
            "start": {
              "line": 1,
              "column": 9,
              "index": 9
            },
            "end": {
              "line": 1,
              "column": 19,
              "index": 19
            },
            "identifierName": "FUNCTION_1"
          },
          "range": [
            9,
            19
          ],
          "name": "FUNCTION_1"
        },
        "generator": false,
        "async": false,
        "params": [
          {
            "type": "Identifier",
            "start": 20,
            "end": 25,
            "loc": {
              "start": {
                "line": 1,
                "column": 20,
                "index": 20
              },
              "end": {
                "line": 1,
                "column": 25,
                "index": 25
              },
              "identifierName": "VAR_1"
            },
            "range": [
              20,
              25
            ],
            "name": "VAR_1"
          }
        ],
        "body": {
          "type": "BlockStatement",
          "start": 27,
          "end": 251,
          "loc": {
            "start": {
              "line": 1,
              "column": 27,
              "index": 27
            },
            "end": {
              "line": 14,
              "column": 1,
              "index": 251
            }
          },
          "range": [
            27,
            251
          ],
          "body": [
            {
              "type": "VariableDeclaration",
              "start": 31,
              "end": 48,
              "loc": {
                "start": {
                  "line": 2,
                  "column": 2,
                  "index": 31
                },
                "end": {
                  "line": 2,
                  "column": 19,
                  "index": 48
                }
              },
              "range": [
                31,
                48
              ],
              "declarations": [
                {
                  "type": "VariableDeclarator",
                  "start": 35,
                  "end": 47,
                  "loc": {
                    "start": {
                      "line": 2,
                      "column": 6,
                      "index": 35
                    },
                    "end": {
                      "line": 2,
                      "column": 18,
                      "index": 47
                    }
                  },
                  "range": [
                    35,
                    47
                  ],
                  "id": {
                    "type": "Identifier",
                    "start": 35,
                    "end": 40,
                    "loc": {
                      "start": {
                        "line": 2,
                        "column": 6,
                        "index": 35
                      },
                      "end": {
                        "line": 2,
                        "column": 11,
                        "index": 40
                      },
                      "identifierName": "VAR_2"
                    },
                    "range": [
                      35,
                      40
                    ],
                    "name": "VAR_2"
                  },
                  "init": {
                    "type": "StringLiteral",
                    "start": 43,
                    "end": 47,
                    "loc": {
                      "start": {
                        "line": 2,
                        "column": 14,
                        "index": 43
                      },
                      "end": {
                        "line": 2,
                        "column": 18,
                        "index": 47
                      }
                    },
                    "range": [
                      43,
                      47
                    ],
                    "extra": {
                      "rawValue": "KB",
                      "raw": "\"KB\""
                    },
                    "value": "KB"
                  }
                }
              ],
              "kind": "var"
            },
            {
              "type": "ExpressionStatement",
              "start": 51,
              "end": 65,
              "loc": {
                "start": {
                  "line": 3,
                  "column": 2,
                  "index": 51
                },
                "end": {
                  "line": 3,
                  "column": 16,
                  "index": 65
                }
              },
              "range": [
                51,
                65
              ],
              "expression": {
                "type": "AssignmentExpression",
                "start": 51,
                "end": 64,
                "loc": {
                  "start": {
                    "line": 3,
                    "column": 2,
                    "index": 51
                  },
                  "end": {
                    "line": 3,
                    "column": 15,
                    "index": 64
                  }
                },
                "range": [
                  51,
                  64
                ],
                "operator": "/=",
                "left": {
                  "type": "Identifier",
                  "start": 51,
                  "end": 56,
                  "loc": {
                    "start": {
                      "line": 3,
                      "column": 2,
                      "index": 51
                    },
                    "end": {
                      "line": 3,
                      "column": 7,
                      "index": 56
                    },
                    "identifierName": "VAR_1"
                  },
                  "range": [
                    51,
                    56
                  ],
                  "name": "VAR_1"
                },
                "right": {
                  "type": "NumericLiteral",
                  "start": 60,
                  "end": 64,
                  "loc": {
                    "start": {
                      "line": 3,
                      "column": 11,
                      "index": 60
                    },
                    "end": {
                      "line": 3,
                      "column": 15,
                      "index": 64
                    }
                  },
                  "range": [
                    60,
                    64
                  ],
                  "extra": {
                    "rawValue": 1024,
                    "raw": "1024"
                  },
                  "value": 1024
                }
              }
            },
            {
              "type": "IfStatement",
              "start": 68,
              "end": 128,
              "loc": {
                "start": {
                  "line": 4,
                  "column": 2,
                  "index": 68
                },
                "end": {
                  "line": 7,
                  "column": 3,
                  "index": 128
                }
              },
              "range": [
                68,
                128
              ],
              "test": {
                "type": "BinaryExpression",
                "start": 72,
                "end": 84,
                "loc": {
                  "start": {
                    "line": 4,
                    "column": 6,
                    "index": 72
                  },
                  "end": {
                    "line": 4,
                    "column": 18,
                    "index": 84
                  }
                },
                "range": [
                  72,
                  84
                ],
                "left": {
                  "type": "Identifier",
                  "start": 72,
                  "end": 77,
                  "loc": {
                    "start": {
                      "line": 4,
                      "column": 6,
                      "index": 72
                    },
                    "end": {
                      "line": 4,
                      "column": 11,
                      "index": 77
                    },
                    "identifierName": "VAR_1"
                  },
                  "range": [
                    72,
                    77
                  ],
                  "name": "VAR_1"
                },
                "operator": ">",
                "right": {
                  "type": "NumericLiteral",
                  "start": 80,
                  "end": 84,
                  "loc": {
                    "start": {
                      "line": 4,
                      "column": 14,
                      "index": 80
                    },
                    "end": {
                      "line": 4,
                      "column": 18,
                      "index": 84
                    }
                  },
                  "range": [
                    80,
                    84
                  ],
                  "extra": {
                    "rawValue": 1024,
                    "raw": "1024"
                  },
                  "value": 1024
                }
              },
              "consequent": {
                "type": "BlockStatement",
                "start": 86,
                "end": 128,
                "loc": {
                  "start": {
                    "line": 4,
                    "column": 20,
                    "index": 86
                  },
                  "end": {
                    "line": 7,
                    "column": 3,
                    "index": 128
                  }
                },
                "range": [
                  86,
                  128
                ],
                "body": [
                  {
                    "type": "ExpressionStatement",
                    "start": 92,
                    "end": 106,
                    "loc": {
                      "start": {
                        "line": 5,
                        "column": 4,
                        "index": 92
                      },
                      "end": {
                        "line": 5,
                        "column": 18,
                        "index": 106
                      }
                    },
                    "range": [
                      92,
                      106
                    ],
                    "expression": {
                      "type": "AssignmentExpression",
                      "start": 92,
                      "end": 105,
                      "loc": {
                        "start": {
                          "line": 5,
                          "column": 4,
                          "index": 92
                        },
                        "end": {
                          "line": 5,
                          "column": 17,
                          "index": 105
                        }
                      },
                      "range": [
                        92,
                        105
                      ],
                      "operator": "/=",
                      "left": {
                        "type": "Identifier",
                        "start": 92,
                        "end": 97,
                        "loc": {
                          "start": {
                            "line": 5,
                            "column": 4,
                            "index": 92
                          },
                          "end": {
                            "line": 5,
                            "column": 9,
                            "index": 97
                          },
                          "identifierName": "VAR_1"
                        },
                        "range": [
                          92,
                          97
                        ],
                        "name": "VAR_1"
                      },
                      "right": {
                        "type": "NumericLiteral",
                        "start": 101,
                        "end": 105,
                        "loc": {
                          "start": {
                            "line": 5,
                            "column": 13,
                            "index": 101
                          },
                          "end": {
                            "line": 5,
                            "column": 17,
                            "index": 105
                          }
                        },
                        "range": [
                          101,
                          105
                        ],
                        "extra": {
                          "rawValue": 1024,
                          "raw": "1024"
                        },
                        "value": 1024
                      }
                    }
                  },
                  {
                    "type": "ExpressionStatement",
                    "start": 111,
                    "end": 124,
                    "loc": {
                      "start": {
                        "line": 6,
                        "column": 4,
                        "index": 111
                      },
                      "end": {
                        "line": 6,
                        "column": 17,
                        "index": 124
                      }
                    },
                    "range": [
                      111,
                      124
                    ],
                    "expression": {
                      "type": "AssignmentExpression",
                      "start": 111,
                      "end": 123,
                      "loc": {
                        "start": {
                          "line": 6,
                          "column": 4,
                          "index": 111
                        },
                        "end": {
                          "line": 6,
                          "column": 16,
                          "index": 123
                        }
                      },
                      "range": [
                        111,
                        123
                      ],
                      "operator": "=",
                      "left": {
                        "type": "Identifier",
                        "start": 111,
                        "end": 116,
                        "loc": {
                          "start": {
                            "line": 6,
                            "column": 4,
                            "index": 111
                          },
                          "end": {
                            "line": 6,
                            "column": 9,
                            "index": 116
                          },
                          "identifierName": "VAR_2"
                        },
                        "range": [
                          111,
                          116
                        ],
                        "name": "VAR_2"
                      },
                      "right": {
                        "type": "StringLiteral",
                        "start": 119,
                        "end": 123,
                        "loc": {
                          "start": {
                            "line": 6,
                            "column": 12,
                            "index": 119
                          },
                          "end": {
                            "line": 6,
                            "column": 16,
                            "index": 123
                          }
                        },
                        "range": [
                          119,
                          123
                        ],
                        "extra": {
                          "rawValue": "MB",
                          "raw": "\"MB\""
                        },
                        "value": "MB"
                      }
                    }
                  }
                ],
                "directives": []
              },
              "alternate": null
            },
            {
              "type": "IfStatement",
              "start": 131,
              "end": 191,
              "loc": {
                "start": {
                  "line": 8,
                  "column": 2,
                  "index": 131
                },
                "end": {
                  "line": 11,
                  "column": 3,
                  "index": 191
                }
              },
              "range": [
                131,
                191
              ],
              "test": {
                "type": "BinaryExpression",
                "start": 135,
                "end": 147,
                "loc": {
                  "start": {
                    "line": 8,
                    "column": 6,
                    "index": 135
                  },
                  "end": {
                    "line": 8,
                    "column": 18,
                    "index": 147
                  }
                },
                "range": [
                  135,
                  147
                ],
                "left": {
                  "type": "Identifier",
                  "start": 135,
                  "end": 140,
                  "loc": {
                    "start": {
                      "line": 8,
                      "column": 6,
                      "index": 135
                    },
                    "end": {
                      "line": 8,
                      "column": 11,
                      "index": 140
                    },
                    "identifierName": "VAR_1"
                  },
                  "range": [
                    135,
                    140
                  ],
                  "name": "VAR_1"
                },
                "operator": ">",
                "right": {
                  "type": "NumericLiteral",
                  "start": 143,
                  "end": 147,
                  "loc": {
                    "start": {
                      "line": 8,
                      "column": 14,
                      "index": 143
                    },
                    "end": {
                      "line": 8,
                      "column": 18,
                      "index": 147
                    }
                  },
                  "range": [
                    143,
                    147
                  ],
                  "extra": {
                    "rawValue": 1024,
                    "raw": "1024"
                  },
                  "value": 1024
                }
              },
              "consequent": {
                "type": "BlockStatement",
                "start": 149,
                "end": 191,
                "loc": {
                  "start": {
                    "line": 8,
                    "column": 20,
                    "index": 149
                  },
                  "end": {
                    "line": 11,
                    "column": 3,
                    "index": 191
                  }
                },
                "range": [
                  149,
                  191
                ],
                "body": [
                  {
                    "type": "ExpressionStatement",
                    "start": 155,
                    "end": 169,
                    "loc": {
                      "start": {
                        "line": 9,
                        "column": 4,
                        "index": 155
                      },
                      "end": {
                        "line": 9,
                        "column": 18,
                        "index": 169
                      }
                    },
                    "range": [
                      155,
                      169
                    ],
                    "expression": {
                      "type": "AssignmentExpression",
                      "start": 155,
                      "end": 168,
                      "loc": {
                        "start": {
                          "line": 9,
                          "column": 4,
                          "index": 155
                        },
                        "end": {
                          "line": 9,
                          "column": 17,
                          "index": 168
                        }
                      },
                      "range": [
                        155,
                        168
                      ],
                      "operator": "/=",
                      "left": {
                        "type": "Identifier",
                        "start": 155,
                        "end": 160,
                        "loc": {
                          "start": {
                            "line": 9,
                            "column": 4,
                            "index": 155
                          },
                          "end": {
                            "line": 9,
                            "column": 9,
                            "index": 160
                          },
                          "identifierName": "VAR_1"
                        },
                        "range": [
                          155,
                          160
                        ],
                        "name": "VAR_1"
                      },
                      "right": {
                        "type": "NumericLiteral",
                        "start": 164,
                        "end": 168,
                        "loc": {
                          "start": {
                            "line": 9,
                            "column": 13,
                            "index": 164
                          },
                          "end": {
                            "line": 9,
                            "column": 17,
                            "index": 168
                          }
                        },
                        "range": [
                          164,
                          168
                        ],
                        "extra": {
                          "rawValue": 1024,
                          "raw": "1024"
                        },
                        "value": 1024
                      }
                    }
                  },
                  {
                    "type": "ExpressionStatement",
                    "start": 174,
                    "end": 187,
                    "loc": {
                      "start": {
                        "line": 10,
                        "column": 4,
                        "index": 174
                      },
                      "end": {
                        "line": 10,
                        "column": 17,
                        "index": 187
                      }
                    },
                    "range": [
                      174,
                      187
                    ],
                    "expression": {
                      "type": "AssignmentExpression",
                      "start": 174,
                      "end": 186,
                      "loc": {
                        "start": {
                          "line": 10,
                          "column": 4,
                          "index": 174
                        },
                        "end": {
                          "line": 10,
                          "column": 16,
                          "index": 186
                        }
                      },
                      "range": [
                        174,
                        186
                      ],
                      "operator": "=",
                      "left": {
                        "type": "Identifier",
                        "start": 174,
                        "end": 179,
                        "loc": {
                          "start": {
                            "line": 10,
                            "column": 4,
                            "index": 174
                          },
                          "end": {
                            "line": 10,
                            "column": 9,
                            "index": 179
                          },
                          "identifierName": "VAR_2"
                        },
                        "range": [
                          174,
                          179
                        ],
                        "name": "VAR_2"
                      },
                      "right": {
                        "type": "StringLiteral",
                        "start": 182,
                        "end": 186,
                        "loc": {
                          "start": {
                            "line": 10,
                            "column": 12,
                            "index": 182
                          },
                          "end": {
                            "line": 10,
                            "column": 16,
                            "index": 186
                          }
                        },
                        "range": [
                          182,
                          186
                        ],
                        "extra": {
                          "rawValue": "GB",
                          "raw": "\"GB\""
                        },
                        "value": "GB"
                      }
                    }
                  }
                ],
                "directives": []
              },
              "alternate": null
            },
            {
              "type": "ExpressionStatement",
              "start": 194,
              "end": 233,
              "loc": {
                "start": {
                  "line": 12,
                  "column": 2,
                  "index": 194
                },
                "end": {
                  "line": 12,
                  "column": 41,
                  "index": 233
                }
              },
              "range": [
                194,
                233
              ],
              "expression": {
                "type": "AssignmentExpression",
                "start": 194,
                "end": 232,
                "loc": {
                  "start": {
                    "line": 12,
                    "column": 2,
                    "index": 194
                  },
                  "end": {
                    "line": 12,
                    "column": 40,
                    "index": 232
                  }
                },
                "range": [
                  194,
                  232
                ],
                "operator": "=",
                "left": {
                  "type": "Identifier",
                  "start": 194,
                  "end": 199,
                  "loc": {
                    "start": {
                      "line": 12,
                      "column": 2,
                      "index": 194
                    },
                    "end": {
                      "line": 12,
                      "column": 7,
                      "index": 199
                    },
                    "identifierName": "VAR_1"
                  },
                  "range": [
                    194,
                    199
                  ],
                  "name": "VAR_1"
                },
                "right": {
                  "type": "BinaryExpression",
                  "start": 202,
                  "end": 232,
                  "loc": {
                    "start": {
                      "line": 12,
                      "column": 10,
                      "index": 202
                    },
                    "end": {
                      "line": 12,
                      "column": 40,
                      "index": 232
                    }
                  },
                  "range": [
                    202,
                    232
                  ],
                  "left": {
                    "type": "BinaryExpression",
                    "start": 202,
                    "end": 224,
                    "loc": {
                      "start": {
                        "line": 12,
                        "column": 10,
                        "index": 202
                      },
                      "end": {
                        "line": 12,
                        "column": 32,
                        "index": 224
                      }
                    },
                    "range": [
                      202,
                      224
                    ],
                    "left": {
                      "type": "CallExpression",
                      "start": 202,
                      "end": 218,
                      "loc": {
                        "start": {
                          "line": 12,
                          "column": 10,
                          "index": 202
                        },
                        "end": {
                          "line": 12,
                          "column": 26,
                          "index": 218
                        }
                      },
                      "range": [
                        202,
                        218
                      ],
                      "callee": {
                        "type": "MemberExpression",
                        "start": 202,
                        "end": 215,
                        "loc": {
                          "start": {
                            "line": 12,
                            "column": 10,
                            "index": 202
                          },
                          "end": {
                            "line": 12,
                            "column": 23,
                            "index": 215
                          }
                        },
                        "range": [
                          202,
                          215
                        ],
                        "object": {
                          "type": "Identifier",
                          "start": 202,
                          "end": 207,
                          "loc": {
                            "start": {
                              "line": 12,
                              "column": 10,
                              "index": 202
                            },
                            "end": {
                              "line": 12,
                              "column": 15,
                              "index": 207
                            },
                            "identifierName": "VAR_1"
                          },
                          "range": [
                            202,
                            207
                          ],
                          "name": "VAR_1"
                        },
                        "computed": false,
                        "property": {
                          "type": "Identifier",
                          "start": 208,
                          "end": 215,
                          "loc": {
                            "start": {
                              "line": 12,
                              "column": 16,
                              "index": 208
                            },
                            "end": {
                              "line": 12,
                              "column": 23,
                              "index": 215
                            },
                            "identifierName": "toFixed"
                          },
                          "range": [
                            208,
                            215
                          ],
                          "name": "toFixed"
                        }
                      },
                      "arguments": [
                        {
                          "type": "NumericLiteral",
                          "start": 216,
                          "end": 217,
                          "loc": {
                            "start": {
                              "line": 12,
                              "column": 24,
                              "index": 216
                            },
                            "end": {
                              "line": 12,
                              "column": 25,
                              "index": 217
                            }
                          },
                          "range": [
                            216,
                            217
                          ],
                          "extra": {
                            "rawValue": 2,
                            "raw": "2"
                          },
                          "value": 2
                        }
                      ]
                    },
                    "operator": "+",
                    "right": {
                      "type": "StringLiteral",
                      "start": 221,
                      "end": 224,
                      "loc": {
                        "start": {
                          "line": 12,
                          "column": 29,
                          "index": 221
                        },
                        "end": {
                          "line": 12,
                          "column": 32,
                          "index": 224
                        }
                      },
                      "range": [
                        221,
                        224
                      ],
                      "extra": {
                        "rawValue": " ",
                        "raw": "\" \""
                      },
                      "value": " "
                    }
                  },
                  "operator": "+",
                  "right": {
                    "type": "Identifier",
                    "start": 227,
                    "end": 232,
                    "loc": {
                      "start": {
                        "line": 12,
                        "column": 35,
                        "index": 227
                      },
                      "end": {
                        "line": 12,
                        "column": 40,
                        "index": 232
                      },
                      "identifierName": "VAR_2"
                    },
                    "range": [
                      227,
                      232
                    ],
                    "name": "VAR_2"
                  }
                }
              }
            },
            {
              "type": "ReturnStatement",
              "start": 236,
              "end": 249,
              "loc": {
                "start": {
                  "line": 13,
                  "column": 2,
                  "index": 236
                },
                "end": {
                  "line": 13,
                  "column": 15,
                  "index": 249
                }
              },
              "range": [
                236,
                249
              ],
              "argument": {
                "type": "Identifier",
                "start": 243,
                "end": 248,
                "loc": {
                  "start": {
                    "line": 13,
                    "column": 9,
                    "index": 243
                  },
                  "end": {
                    "line": 13,
                    "column": 14,
                    "index": 248
                  },
                  "identifierName": "VAR_1"
                },
                "range": [
                  243,
                  248
                ],
                "name": "VAR_1"
              }
            }
          ],
          "directives": []
        }
      },
      {
        "type": "ExpressionStatement",
        "start": 252,
        "end": 275,
        "loc": {
          "start": {
            "line": 15,
            "column": 0,
            "index": 252
          },
          "end": {
            "line": 15,
            "column": 23,
            "index": 275
          }
        },
        "range": [
          252,
          275
        ],
        "expression": {
          "type": "CallExpression",
          "start": 252,
          "end": 274,
          "loc": {
            "start": {
              "line": 15,
              "column": 0,
              "index": 252
            },
            "end": {
              "line": 15,
              "column": 22,
              "index": 274
            }
          },
          "range": [
            252,
            274
          ],
          "callee": {
            "type": "Identifier",
            "start": 252,
            "end": 262,
            "loc": {
              "start": {
                "line": 15,
                "column": 0,
                "index": 252
              },
              "end": {
                "line": 15,
                "column": 10,
                "index": 262
              },
              "identifierName": "FUNCTION_1"
            },
            "range": [
              252,
              262
            ],
            "name": "FUNCTION_1"
          },
          "arguments": [
            {
              "type": "NumericLiteral",
              "start": 263,
              "end": 273,
              "loc": {
                "start": {
                  "line": 15,
                  "column": 11,
                  "index": 263
                },
                "end": {
                  "line": 15,
                  "column": 21,
                  "index": 273
                }
              },
              "range": [
                263,
                273
              ],
              "extra": {
                "rawValue": 2738472847,
                "raw": "2738472847"
              },
              "value": 2738472847
            }
          ]
        }
      }
    ],
    "directives": [],
    "extra": {
      "topLevelAwait": false
    }
  },
  "comments": []
}